wittrans/__init__.py
wittrans/functions.py
wittrans/language_mappings.py
wittrans/main.py
wittrans-0.6.1.dist-info/licenses/LICENSE
wittrans-0.6.1.dist-info/METADATA
wittrans-0.6.1.dist-info/WHEEL
wittrans-0.6.1.dist-info/entry_points.txt
wittrans-0.6.1.dist-info/top_level.txt
wittrans-0.6.1.dist-info/RECORD
