Metadata-Version: 2.4
Name: wittrans
Version: 0.6.1
Summary: Search for translation strings in Linux distributions
Author-email: Jiri Grönroos <jiri.gronroos@iki.fi>
License-Expression: AGPL-3.0-or-later
Project-URL: Homepage, https://codeberg.org/artnay/wittrans
Project-URL: Issues, https://codeberg.org/artnay/wittrans/issues
Project-URL: Repository, https://codeberg.org/artnay/wittrans
Project-URL: Changelog, https://codeberg.org/artnay/wittrans/src/branch/main/CHANGELOG.md
Keywords: translation,localization,l10n,linux,gettext
Classifier: Development Status :: 4 - Beta
Classifier: Environment :: Console
Classifier: Intended Audience :: Developers
Classifier: Operating System :: POSIX :: Linux
Classifier: Programming Language :: Python :: 3
Classifier: Programming Language :: Python :: 3.12
Classifier: Programming Language :: Python :: 3.13
Classifier: Programming Language :: Python :: 3.14
Classifier: Topic :: Software Development :: Localization
Requires-Python: >=3.12
License-File: LICENSE
Requires-Dist: polib>=1.2.0
Requires-Dist: rich>=14.1.0
Dynamic: license-file
